LICENSE
README.md
setup.py
easypl/__init__.py
easypl/callbacks/__init__.py
easypl/callbacks/finetuners/__init__.py
easypl/callbacks/finetuners/optimizer_initializator.py
easypl/callbacks/finetuners/sequential_tuner.py
easypl/callbacks/loggers/__init__.py
easypl/callbacks/loggers/base.py
easypl/callbacks/loggers/base_image.py
easypl/callbacks/loggers/collector.py
easypl/callbacks/loggers/image_classification.py
easypl/callbacks/loggers/image_detection.py
easypl/callbacks/loggers/image_gan.py
easypl/callbacks/loggers/image_segmentation.py
easypl/callbacks/mixers/__init__.py
easypl/callbacks/mixers/base.py
easypl/callbacks/mixers/cutmix.py
easypl/callbacks/mixers/mixup.py
easypl/callbacks/mixers/mosaic.py
easypl/callbacks/predictors/__init__.py
easypl/callbacks/predictors/base.py
easypl/callbacks/predictors/base_image.py
easypl/callbacks/predictors/image_classification.py
easypl/datasets/__init__.py
easypl/datasets/base.py
easypl/datasets/utils.py
easypl/datasets/classification/__init__.py
easypl/datasets/classification/csv.py
easypl/datasets/classification/dir.py
easypl/datasets/detection/__init__.py
easypl/datasets/detection/csv.py
easypl/datasets/segmentation/__init__.py
easypl/datasets/segmentation/csv.py
easypl/learners/__init__.py
easypl/learners/base.py
easypl/learners/classification.py
easypl/learners/detection.py
easypl/learners/gan.py
easypl/learners/recognition.py
easypl/learners/segmentation.py
easypl/losses/__init__.py
easypl/losses/segmentation/__init__.py
easypl/losses/segmentation/diceloss.py
easypl/lr_schedulers/__init__.py
easypl/lr_schedulers/wrapper.py
easypl/metrics/__init__.py
easypl/metrics/base.py
easypl/metrics/torch.py
easypl/metrics/utils.py
easypl/metrics/classification/__init__.py
easypl/metrics/classification/search_accuracy.py
easypl/metrics/classification/search_mean_average_precision.py
easypl/metrics/detection/__init__.py
easypl/metrics/detection/base.py
easypl/metrics/detection/f_beta.py
easyplib.egg-info/PKG-INFO
easyplib.egg-info/SOURCES.txt
easyplib.egg-info/dependency_links.txt
easyplib.egg-info/requires.txt
easyplib.egg-info/top_level.txt