Metadata-Version: 2.1
Name: easyplib
Version: 0.8
Summary: UNKNOWN
Home-page: https://github.com/tam2511/EasyPL
Author: Alexander Timofeev
Author-email: tam2511@mail.ru
License: UNKNOWN
Platform: UNKNOWN
Classifier: Programming Language :: Python :: 3
Classifier: License :: OSI Approved :: MIT License
Classifier: Operating System :: OS Independent
Requires-Python: >=3.6
Provides-Extra: classification
Provides-Extra: segmentation
Provides-Extra: detection
Provides-Extra: gan
Provides-Extra: all
